{"grouping_venue_conditions":"All","key_is_year_rolling":"1","key_year":"2018","key_bat_side":"All","venue_id":"4","venue_name":"Guaranteed Rate Field","main_team_id":"145","name_display_club":"White Sox","n_pa":"21276","index_runs":"96","index_hardhit":"96","index_woba":"98","index_wobacon":"100","index_xwobacon":"97","index_xbacon":"98","index_obp":"98","index_so":"104","index_bb":"97","index_bacon":"99","index_hits":"97","index_1b":"98","index_2b":"91","index_3b":"87","index_hr":"108","year_range":"2016-2018","venue_url":"https:\/\/baseballsavant.mlb.com\/leaderboard\/statcast-venue?venueId=4"}